pyensmallen_experimental-0.2.7128.dist-info/RECORD
pyensmallen_experimental-0.2.7128.dist-info/WHEEL
pyensmallen_experimental-0.2.7128.dist-info/LICENSE.txt
pyensmallen_experimental-0.2.7128.dist-info/METADATA
pyensmallen_experimental/newton_type.hpp
pyensmallen_experimental/gmm.py
pyensmallen_experimental/_pyensmallen.cpython-310-darwin.so
pyensmallen_experimental/__init__.py
pyensmallen_experimental/first_order.hpp
pyensmallen_experimental/losses.py
pyensmallen_experimental/constrained.hpp
pyensmallen_experimental/utils.hpp
pyensmallen_experimental/.dylibs/libarpack.2.1.0.dylib
pyensmallen_experimental/.dylibs/libomp.dylib
pyensmallen_experimental/.dylibs/libgfortran.5.dylib
pyensmallen_experimental/.dylibs/libarmadillo.14.4.3.dylib
pyensmallen_experimental/.dylibs/libquadmath.0.dylib
pyensmallen_experimental/.dylibs/libgcc_s.1.1.dylib
pyensmallen_experimental/.dylibs/libopenblas.0.dylib
