Metadata-Version: 2.1
Name: pyensmallen-experimental
Version: 0.2.7128
Summary: Python bindings for the Ensmallen library.
Author-Email: Apoorva Lal <lal.apoorva@gmail.com>, Matthew Wardrop <mpwardrop@gmail.com>
License: MIT License
Requires-Python: >=3.10
